LICENSE
README.rst
pygments_cache.py
setup.py
pygments_cache.egg-info/PKG-INFO
pygments_cache.egg-info/SOURCES.txt
pygments_cache.egg-info/dependency_links.txt
pygments_cache.egg-info/not-zip-safe
pygments_cache.egg-info/requires.txt
pygments_cache.egg-info/top_level.txt