Metadata-Version: 1.1
Name: pygments-cache
Version: 0.1.3
Summary: A fast, drop-in replacement for pygments `get_*()` and `guess_*()` funtions
Home-page: https://github.com/xonsh/pygments-cache
Author: The xonsh developers
Author-email: xonsh@googlegroups.com
License: BSD 3-clause
Download-URL: https://github.com/xonsh/pygments-cache/zipball/0.1.3
Platform: UNKNOWN
Classifier: License :: OSI Approved
Classifier: Intended Audience :: Developers
Classifier: Programming Language :: Python
Classifier: Topic :: Utilities
